aiooss
