Metadata-Version: 1.1
Name: aiooss
Version: 0.1.2
Summary: A async aliyun OSS library.
Home-page: https://github.com/codeif/aiooss
Author: codeif
Author-email: me@codeif.com
License: MIT
Platform: UNKNOWN
Classifier: Development Status :: 5 - Production/Stable
Classifier: Intended Audience :: Developers
Classifier: License :: OSI Approved :: MIT License
Classifier: Programming Language :: Python :: 3.5
Classifier: Programming Language :: Python :: 3.6
